LICENSE
README.md
setup.cfg
setup.py
humanmark/__init__.py
humanmark/ast.py
humanmark/cli.py
humanmark.egg-info/PKG-INFO
humanmark.egg-info/SOURCES.txt
humanmark.egg-info/dependency_links.txt
humanmark.egg-info/entry_points.txt
humanmark.egg-info/not-zip-safe
humanmark.egg-info/requires.txt
humanmark.egg-info/top_level.txt
humanmark/backends/__init__.py
humanmark/backends/markdown_it.py
humanmark/render/__init__.py
humanmark/render/json.py
humanmark/render/markdown.py
humanmark/render/txt.py